truthordare/__init__.py
truthordare/funtions.py
truthordare.py-0.0.7.dist-info/LICENSE
truthordare.py-0.0.7.dist-info/METADATA
truthordare.py-0.0.7.dist-info/WHEEL
truthordare.py-0.0.7.dist-info/top_level.txt
truthordare.py-0.0.7.dist-info/RECORD
